pyger/__init__.py
pyger/base.py
pyger-0.1.dist-info/DESCRIPTION.rst
pyger-0.1.dist-info/LICENSE.txt
pyger-0.1.dist-info/METADATA
pyger-0.1.dist-info/RECORD
pyger-0.1.dist-info/WHEEL
pyger-0.1.dist-info/metadata.json
pyger-0.1.dist-info/top_level.txt
