Metadata-Version: 2.0
Name: pyger
Version: 0.1
Summary: PyGER - Python Generic Extensible Router
Home-page: https://github.com/sseg/pyger
Author: Steven Seguin
Author-email: steven.seguin@gmail.com
License: BSD
Platform: UNKNOWN
Classifier: Programming Language :: Python :: 3
Provides-Extra: test
Requires-Dist: flake8; extra == 'test'
Requires-Dist: pytest; extra == 'test'
Requires-Dist: pytest-cov; extra == 'test'
